darkdetect/__init__.py
darkdetect/_dummy.py
darkdetect/_linux_detect.py
darkdetect/_mac_detect.py
darkdetect/_windows_detect.py
darkdetect-0.4.0.dist-info/LICENSE
darkdetect-0.4.0.dist-info/METADATA
darkdetect-0.4.0.dist-info/WHEEL
darkdetect-0.4.0.dist-info/top_level.txt
darkdetect-0.4.0.dist-info/RECORD
