Metadata-Version: 2.1
Name: darkdetect
Version: 0.4.0
Summary: Detect OS Dark Mode from Python
Home-page: http://github.com/albertosottile/darkdetect
Author: Alberto Sottile
Author-email: asottile@gmail.com
License: BSD
Download-URL: http://github.com/albertosottile/darkdetect/releases
Platform: UNKNOWN
Classifier: License :: OSI Approved :: BSD License
Classifier: Operating System :: MacOS :: MacOS X
Classifier: Programming Language :: Python :: 2
Classifier: Programming Language :: Python :: 2.7
Classifier: Programming Language :: Python :: 3
Classifier: Programming Language :: Python :: 3.2
Classifier: Programming Language :: Python :: 3.3
Classifier: Programming Language :: Python :: 3.4
Classifier: Programming Language :: Python :: 3.5
Classifier: Programming Language :: Python :: 3.6
Classifier: Programming Language :: Python :: 3.7
Classifier: Programming Language :: Python :: 3.8
Classifier: Programming Language :: Python :: 3.9
License-File: LICENSE
